anychat/__init__.py
anychat/model.py
anychat-0.1.1.dist-info/METADATA
anychat-0.1.1.dist-info/WHEEL
anychat-0.1.1.dist-info/licenses/LICENSE
anychat-0.1.1.dist-info/RECORD
