Metadata-Version: 2.3
Name: anychat
Version: 0.1.1
Summary: 自定义ChatModel
Project-URL: Repository, https://gitee.com/kin9-0rz/anychat
Author-email: kin9-0rz <kin9-0rz@outlook.com>
Requires-Python: >=3.12
Requires-Dist: httpx==0.27.2
Requires-Dist: langchain-core>=0.3.21
Requires-Dist: langchain>=0.0.27
